radius_wallets/web3/__init__.py
radius_wallets/web3/wallet.py
radius_ai_agent_sdk_wallet_web3-1.0.0.dist-info/METADATA
radius_ai_agent_sdk_wallet_web3-1.0.0.dist-info/WHEEL
radius_ai_agent_sdk_wallet_web3-1.0.0.dist-info/top_level.txt
radius_ai_agent_sdk_wallet_web3-1.0.0.dist-info/RECORD
